HardView/HardView.so
HardView/LiveView.so
HardView/__init__.py
hardview.libs/libsensors-b2438416.so.4.4.0
hardview-3.2.0.dist-info/METADATA
hardview-3.2.0.dist-info/WHEEL
hardview-3.2.0.dist-info/top_level.txt
hardview-3.2.0.dist-info/RECORD
hardview-3.2.0.dist-info/licenses/LICENSE
hardview-3.2.0.dist-info/licenses/LICENSE.GPL3
