Metadata-Version: 2.4
Name: HardView
Version: 3.2.0
Summary: A comprehensive Python library for collecting hardware information and real-time performance monitoring.
Home-page: https://github.com/gafoo173/HardView
Author: gafoo
Author-email: omarwaled3374@gmail.com
License: MIT
Project-URL: Bug Reports, https://github.com/gafoo173/HardView/issues
Project-URL: Source, https://github.com/gafoo173/HardView
Keywords: hardware system monitoring performance cpu ram disk network gpu bios windows linux wmi real-time live
Classifier: Programming Language :: Python :: 3.8
Classifier: Programming Language :: Python :: 3.9
Classifier: Programming Language :: Python :: 3.10
Classifier: Programming Language :: Python :: 3.11
Classifier: Programming Language :: Python :: 3.12
Classifier: Operating System :: Microsoft :: Windows
Classifier: Operating System :: POSIX :: Linux
Classifier: Topic :: System :: Hardware
Classifier: Topic :: System :: Monitoring
Requires-Python: >=3.7
License-File: LICENSE
License-File: LICENSE.GPL3
Requires-Dist: pybind11>=2.6
Provides-Extra: dev
Requires-Dist: pytest>=6.0; extra == "dev"
Dynamic: author
Dynamic: author-email
Dynamic: classifier
Dynamic: description
Dynamic: description-content-type
Dynamic: home-page
Dynamic: keywords
Dynamic: license
Dynamic: license-file
Dynamic: project-url
Dynamic: provides-extra
Dynamic: requires-dist
Dynamic: requires-python
Dynamic: summary
